[
  {
    "created_at": "2022-11-02T12:48:27.000Z",
    "text": "&lt;SSR出現率2倍&gt;\n圧倒的なグラフィックと壮大な世界観。\nかつてない物語をスマホRPGに！\n\n【11月3日 18:59まで】\n#グラブル\n#レジェフェス\n#アリア",
    "edit_history_tweet_ids": ["1587788727710994432"],
    "id": "1587788727710994432",
    "author_id": "1549889018"
  },
  {
    "created_at": "2022-11-02T12:46:31.000Z",
    "text": "&lt;SSR出現率2倍&gt;\n圧倒的なグラフィックと壮大な世界観。\nかつてない物語をスマホRPGに！\n\n【11月3日 18:59まで】\n#グラブル\n#レジェフェス\n#ユエル\n#ソシエ",
    "edit_history_tweet_ids": ["1587788244766191616"],
    "id": "1587788244766191616",
    "author_id": "1549889018"
  },
  {
    "created_at": "2022-11-02T12:44:18.000Z",
    "text": "&lt;SSR出現率2倍&gt;\n圧倒的なグラフィックと壮大な世界観。\nかつてない物語をスマホRPGに！\n\n【11月3日 18:59まで】\n#グラブル\n#レジェフェス\n#アリア",
    "edit_history_tweet_ids": ["1587787686550478849"],
    "id": "1587787686550478849",
    "author_id": "1549889018"
  },
  {
    "created_at": "2022-11-02T12:43:12.000Z",
    "text": "&lt;SSR出現率2倍&gt;\n圧倒的なグラフィックと壮大な世界観。\nかつてない物語をスマホRPGに！\n\n【11月3日 18:59まで】\n#グラブル\n#レジェフェス\n#ユエル\n#ソシエ",
    "edit_history_tweet_ids": ["1587787408010944512"],
    "id": "1587787408010944512",
    "author_id": "1549889018"
  },
  {
    "created_at": "2022-11-02T03:00:18.000Z",
    "text": "【グランブルーファンタジー】新キャラクターSSレア 「アリア」（CV.茅野愛衣）のバトルモーションを紹介！\nSSレア出現率が2倍にUPのレジェンドフェスは11/3(木)18:59まで開催中！さらに新規追加キャラ解放でLB30と至極の指輪をGET！ #グラブル https://t.co/M1dZBIApSE",
    "edit_history_tweet_ids": ["1587640715386896384"],
    "id": "1587640715386896384",
    "author_id": "1549889018"
  },
  {
    "created_at": "2022-11-02T03:00:08.000Z",
    "text": "【グランブルーファンタジー】【4コマ更新】『ぐらぶるっ！』第2189話「ミサンガ編んだよ編」を公開いたしました！4コマ見るにはこちら（スマホでアクセス！）⇒ https://t.co/lrOs0AfwQs #グラブル https://t.co/pIu8fzXHMU",
    "edit_history_tweet_ids": ["1587640675340013568"],
    "id": "1587640675340013568",
    "author_id": "1549889018"
  },
  {
    "created_at": "2022-11-01T03:11:58.000Z",
    "text": "【グランブルーファンタジー】シルヴァ、ソーンが歌うキャラクターソングCD第26弾「Vanishing Point」の試聴音源を公開いたしました！詳しくはキャラクターソング公式サイトをご確認ください。⇒ https://t.co/WtriHw89cm  #グラブル https://t.co/CQw8e0zzNi",
    "edit_history_tweet_ids": ["1587281265488990208"],
    "id": "1587281265488990208",
    "author_id": "1549889018"
  },
  {
    "created_at": "2022-11-01T03:01:34.000Z",
    "text": "【グランブルーファンタジー】「これからの『グランブルーファンタジー』2022年11月号」を、公式サイト「グラブル最新情報」にて公開いたしました。詳しくは公式サイトにてご確認ください。 ⇒ https://t.co/SpHfdUQEtG #グラブル",
    "edit_history_tweet_ids": ["1587278648750415872"],
    "id": "1587278648750415872",
    "author_id": "1549889018"
  },
  {
    "created_at": "2022-11-01T03:00:16.000Z",
    "text": "【グランブルーファンタジー】新キャラクターSSレア 「永遠の親愛 ユエル＆ソシエ」（CV.植田佳奈/白石涼子）のバトルモーションを紹介！\nSSレア出現率が2倍にUPのレジェンドフェスは11/3(木)18:59まで開催中！さらに新規追加キャラ解放でLB30と至極の指輪をGET！ #グラブル https://t.co/QyCv4Qw9I0",
    "edit_history_tweet_ids": ["1587278321166925825"],
    "id": "1587278321166925825",
    "author_id": "1549889018"
  },
  {
    "created_at": "2022-11-01T03:00:07.000Z",
    "text": "【グランブルーファンタジー】【4コマ更新】『ぐらぶるっ！』第2188話「頼れる！アリアちゃん編」を公開いたしました！4コマ見るにはこちら（スマホでアクセス！）⇒ https://t.co/y710kyPwDR #グラブル https://t.co/rMCNI1E8XF",
    "edit_history_tweet_ids": ["1587278282323824640"],
    "id": "1587278282323824640",
    "author_id": "1549889018"
  }
]
